corelibs/__init__.py
corelibs/_corelibs.py
corelibs/cleanse.py
corelibs/cli.py
corelibs/config.py
corelibs/data.py
corelibs/lazy.py
corelibs/log.py
corelibs/tools.py
corelibs/webdoc.py
corelibs/.corelibs/user_config.py
corelibs/.corelibs/cache/README.md
corelibs/.corelibs/env_backup/README.md
corelibs/.corelibs/templates/README.md
corelibs/.corelibs/templates/scan_dir.xlsx
corelibs/bin/hadoop-3.0.0/bin/hadoop
corelibs/bin/hadoop-3.0.0/bin/hadoop.cmd
corelibs/bin/hadoop-3.0.0/bin/hadoop.dll
corelibs/bin/hadoop-3.0.0/bin/hadoop.exp
corelibs/bin/hadoop-3.0.0/bin/hadoop.lib
corelibs/bin/hadoop-3.0.0/bin/hadoop.pdb
corelibs/bin/hadoop-3.0.0/bin/hdfs
corelibs/bin/hadoop-3.0.0/bin/hdfs.cmd
corelibs/bin/hadoop-3.0.0/bin/hdfs.dll
corelibs/bin/hadoop-3.0.0/bin/hdfs.exp
corelibs/bin/hadoop-3.0.0/bin/hdfs.lib
corelibs/bin/hadoop-3.0.0/bin/hdfs.pdb
corelibs/bin/hadoop-3.0.0/bin/libwinutils.lib
corelibs/bin/hadoop-3.0.0/bin/mapred
corelibs/bin/hadoop-3.0.0/bin/mapred.cmd
corelibs/bin/hadoop-3.0.0/bin/winutils.exe
corelibs/bin/hadoop-3.0.0/bin/winutils.pdb
corelibs/bin/hadoop-3.0.0/bin/yarn
corelibs/bin/hadoop-3.0.0/bin/yarn.cmd
corelibs/bin/linux/7z
corelibs/bin/linux/7z.so
corelibs/bin/linux/7zCon.sfx
corelibs/bin/linux/7za
corelibs/bin/linux/7zr
corelibs/bin/linux/Codecs/Rar.so
corelibs/bin/x64/7za.dll
corelibs/bin/x64/7za.exe
corelibs/bin/x64/7zxa.dll
corelibs/docs/.buildinfo
corelibs/docs/.nojekyll
corelibs/docs/genindex.html
corelibs/docs/index.html
corelibs/docs/objects.inv
corelibs/docs/py-modindex.html
corelibs/docs/role.html
corelibs/docs/search.html
corelibs/docs/searchindex.js
corelibs/docs/_images/corelibs_gui.png
corelibs/docs/_images/decorator_args_dumping.png
corelibs/docs/_images/decorator_status_bar.png
corelibs/docs/_images/decorator_timing.png
corelibs/docs/_images/dict_dumping.png
corelibs/docs/_images/dtale_preview.png
corelibs/docs/_images/is_email.png
corelibs/docs/_images/is_phone_number.png
corelibs/docs/_images/is_well_formatted_schema_log.png
corelibs-1.0.3.dist-info/LICENSE.md
corelibs-1.0.3.dist-info/METADATA
corelibs-1.0.3.dist-info/WHEEL
corelibs-1.0.3.dist-info/entry_points.txt
corelibs-1.0.3.dist-info/top_level.txt
corelibs-1.0.3.dist-info/RECORD
