Metadata-Version: 2.1
Name: corelibs
Version: 1.0.3
Summary: ꧁֍( Point Bleu Pâle )֎꧂
Home-page: UNKNOWN
Author: 宀Kลⴅเ宀 ☬( Michel•TRUONG )☬
Author-email: michel.truong@gmail.com
License: MIT
Platform: UNKNOWN
Classifier: License :: OSI Approved :: MIT License
Classifier: Programming Language :: Python :: 3
Classifier: Programming Language :: Python :: 3.8
Classifier: Programming Language :: Python :: 3.9
Requires-Dist: mkl-service (>=2.3.0)
Requires-Dist: cryptography
Requires-Dist: coloredlogs (>=14.0)
Requires-Dist: colorama (>=0.4.3)
Requires-Dist: schema (>=0.7.2)
Requires-Dist: ipython (>=7.19.0)
Requires-Dist: blessed (>=1.17.11)
Requires-Dist: enlighten (>=1.6.2)
Requires-Dist: click (>=7.1.2)
Requires-Dist: numpy (==1.19.3)
Requires-Dist: numba (==0.51.2)
Requires-Dist: PyYAML (>=5.3.1)
Requires-Dist: yamale (>=3.0.4)
Requires-Dist: sqlparse (>=0.4.1)
Requires-Dist: stackprinter (>=0.2.5)
Requires-Dist: moment (>=0.12.1)
Requires-Dist: pysimplegui (==4.33.0)
Requires-Dist: pyscaffold (>=3.3)
Requires-Dist: dtale (>=1.30.0)
Requires-Dist: pyspark (>=3.0.1)
Requires-Dist: dask[complete]
Requires-Dist: pandasgui (>=0.2.9)
Requires-Dist: openpyxl (>=3.0.6)
Requires-Dist: phonenumbers (>=8.12.19)
Requires-Dist: email-validator (>=1.1.2)
